<?xml version="1.0"?>
<xml><Faculty><name>yuio</name><aboutUs>678</aboutUs><abbreviation>678</abbreviation><costPerCreditHour>678.00</costPerCreditHour><Partner><type>educational</type><name>fghd</name><description>fghwe</description></Partner><Partner><type>educational</type><name>dfg</name><description>qwe</description></Partner></Faculty><Faculty><name>asd</name><aboutUs>qwe</aboutUs><abbreviation>qwe</abbreviation><costPerCreditHour>123.00</costPerCreditHour><Partner><type>company</type><name>qwe</name><description>123</description></Partner><Partner><type>educational</type><name>qwe</name><description>123</description></Partner><Accreditation><name>dfg</name><description>wer</description></Accreditation></Faculty><Faculty><name>qwe</name><aboutUs>qwe</aboutUs><abbreviation>gfh</abbreviation><costPerCreditHour>231.00</costPerCreditHour><Partner><type>company</type><name>sdfg</name><description>dfgret2</description></Partner><Accreditation><name>qwe</name><description>213</description></Accreditation></Faculty></xml>
